labjack_pic/__init__.py
labjack_pic/hacks.py
labjack_pic/lj_pic.py
labjack_pic/u3_manager/__init__.py
labjack_pic/u3_manager/u3_manager.py
labjack_pic-0.0.11.dist-info/LICENSE
labjack_pic-0.0.11.dist-info/METADATA
labjack_pic-0.0.11.dist-info/WHEEL
labjack_pic-0.0.11.dist-info/entry_points.txt
labjack_pic-0.0.11.dist-info/top_level.txt
labjack_pic-0.0.11.dist-info/RECORD
