Metadata-Version: 2.1
Name: labjack_pic
Version: 0.0.11
Summary: Program PIC microcontrollers using LabJack U3
Author-email: Mark Rages <markrages@gmail.com>
Project-URL: Homepage, https://github.com/markrages/labjack_pic/
Project-URL: Bug Tracker, https://github.com/markrages/labjack_pic/issues
Classifier: Programming Language :: Python :: 3
Classifier: License :: OSI Approved :: Apache Software License
Classifier: Operating System :: OS Independent
Requires-Python: >=3.6
License-File: LICENSE
Requires-Dist: intelhex
Requires-Dist: LabJackPython
